peuent.py
peuent-1.1.1.3.dist-info/METADATA
peuent-1.1.1.3.dist-info/WHEEL
peuent-1.1.1.3.dist-info/top_level.txt
peuent-1.1.1.3.dist-info/RECORD
